scitrera_ext_cachetools/__init__.py
scitrera_ext_cachetools-0.0.1.dist-info/METADATA
scitrera_ext_cachetools-0.0.1.dist-info/WHEEL
scitrera_ext_cachetools-0.0.1.dist-info/top_level.txt
scitrera_ext_cachetools-0.0.1.dist-info/RECORD
