Metadata-Version: 2.4
Name: scitrera-ext-cachetools
Version: 0.0.1
Summary: Metapackage for sync and asyncio cachetools
Author: Scitrera LLC
License: BSD-3-Clause
Project-URL: Homepage, https://github.com/scitrera/scitrera-ext-cachetools-python
Project-URL: Issues, https://github.com/scitrera/scitrera-ext-cachetools-python/issues
Classifier: Programming Language :: Python :: 3
Classifier: License :: OSI Approved :: BSD License
Classifier: Operating System :: OS Independent
Requires-Python: >=3.9
Requires-Dist: scitrera-app-framework
Requires-Dist: cachetools
Requires-Dist: asyncache
Provides-Extra: dev
Requires-Dist: pytest; extra == "dev"
Requires-Dist: pytest-asyncio; extra == "dev"
